GNUmakefile
INSTALL
LICENSE
MANIFEST.in
NEWS
README.rst
cheat.el
cpiofile.py
distribute_setup.py
setup.cfg
setup.py
tests.py
cpiofile.egg-info/PKG-INFO
cpiofile.egg-info/SOURCES.txt
cpiofile.egg-info/dependency_links.txt
cpiofile.egg-info/requires.txt
cpiofile.egg-info/top_level.txt
docs/Makefile
docs/source/conf.py
docs/source/index.rst