Metadata-Version: 1.1
Name: cpiofile
Version: 0.002
Summary: A pure python library for reading and writing cpio format archives.
Home-page: http://bitbucket.org/krp/cpiofile
Author: K. Richard Pixley
Author-email: rich@noir.com
License: MIT
Keywords: ar archive
Platform: UNKNOWN
Classifier: Development Status :: 2 - Pre-Alpha
Classifier: Intended Audience :: Developers
Classifier: License :: OSI Approved :: MIT License
Classifier: Natural Language :: English
Classifier: Operating System :: OS Independent
Classifier: Programming Language :: Python
Classifier: Programming Language :: Python :: 2.6
Classifier: Programming Language :: Python :: 2.7
Classifier: Programming Language :: Python :: 3.0
Classifier: Programming Language :: Python :: 3.1
Classifier: Programming Language :: Python :: 3.2
Classifier: Topic :: Software Development :: Libraries :: Python Modules
Provides: cpiofile
